music163/__init__.py
music163-1.3.dist-info/METADATA
music163-1.3.dist-info/WHEEL
music163-1.3.dist-info/top_level.txt
music163-1.3.dist-info/RECORD
